[
  {
    "kind": "order-create",
    "recordedAt": "2026-04-21T00:07:37.325Z",
    "payload": {
      "name": "BEI-ORD-2026-00398",
      "store": "ARANETA GATEWAY - TUNGSTEN CAPITAL HOLDINGS OPC"
    }
  },
  {
    "kind": "mr-create",
    "recordedAt": "2026-04-21T00:07:57.809Z",
    "payload": {
      "name": "MAT-MR-2026-00256",
      "store": "ARANETA GATEWAY - TUNGSTEN CAPITAL HOLDINGS OPC"
    }
  },
  {
    "kind": "wr-create",
    "recordedAt": "2026-04-21T00:08:22.253Z",
    "payload": {
      "name": "BEI-WHR-2026-00102",
      "store": "ARANETA GATEWAY - TUNGSTEN CAPITAL HOLDINGS OPC"
    }
  },
  {
    "kind": "si-create",
    "recordedAt": "2026-04-21T00:08:34.846Z",
    "payload": {
      "name": "ACC-SINV-2026-00092",
      "store": "ARANETA GATEWAY - TUNGSTEN CAPITAL HOLDINGS OPC"
    }
  },
  {
    "kind": "order-create",
    "recordedAt": "2026-04-21T00:09:02.004Z",
    "payload": {
      "name": "BEI-ORD-2026-00399",
      "store": "AYALA FAIRVIEW TERRACES - BEBANG FT INC."
    }
  },
  {
    "kind": "mr-create",
    "recordedAt": "2026-04-21T00:09:18.633Z",
    "payload": {
      "name": "MAT-MR-2026-00257",
      "store": "AYALA FAIRVIEW TERRACES - BEBANG FT INC."
    }
  },
  {
    "kind": "wr-create",
    "recordedAt": "2026-04-21T00:09:36.651Z",
    "payload": {
      "name": "BEI-WHR-2026-00103",
      "store": "AYALA FAIRVIEW TERRACES - BEBANG FT INC."
    }
  },
  {
    "kind": "order-create",
    "recordedAt": "2026-04-21T00:10:45.549Z",
    "payload": {
      "name": "BEI-ORD-2026-00400",
      "store": "AYALA MARKET MARKET - BEBANG MARKET MARKET INC."
    }
  },
  {
    "kind": "order-create",
    "recordedAt": "2026-04-21T00:12:18.039Z",
    "payload": {
      "name": "BEI-ORD-2026-00401",
      "store": "AYALA SOLENAD - HFFM SOLENAD FOOD SERVICES INC."
    }
  },
  {
    "kind": "mr-create",
    "recordedAt": "2026-04-21T00:12:34.835Z",
    "payload": {
      "name": "MAT-MR-2026-00258",
      "store": "AYALA SOLENAD - HFFM SOLENAD FOOD SERVICES INC."
    }
  },
  {
    "kind": "order-create",
    "recordedAt": "2026-04-21T00:14:02.461Z",
    "payload": {
      "name": "BEI-ORD-2026-00402",
      "store": "AYALA UP TOWN CENTER - BEBANG UP TOWN CENTER INC."
    }
  },
  {
    "kind": "mr-create",
    "recordedAt": "2026-04-21T00:14:19.223Z",
    "payload": {
      "name": "MAT-MR-2026-00259",
      "store": "AYALA UP TOWN CENTER - BEBANG UP TOWN CENTER INC."
    }
  },
  {
    "kind": "wr-create",
    "recordedAt": "2026-04-21T00:14:37.187Z",
    "payload": {
      "name": "BEI-WHR-2026-00104",
      "store": "AYALA UP TOWN CENTER - BEBANG UP TOWN CENTER INC."
    }
  },
  {
    "kind": "si-create",
    "recordedAt": "2026-04-21T00:14:45.734Z",
    "payload": {
      "name": "ACC-SINV-2026-00093",
      "store": "AYALA UP TOWN CENTER - BEBANG UP TOWN CENTER INC."
    }
  },
  {
    "kind": "order-create",
    "recordedAt": "2026-04-21T00:15:02.968Z",
    "payload": {
      "name": "BEI-ORD-2026-00403",
      "store": "AYALA VERMOSA - BEBANG MEGA INC."
    }
  },
  {
    "kind": "mr-create",
    "recordedAt": "2026-04-21T00:15:19.180Z",
    "payload": {
      "name": "MAT-MR-2026-00260",
      "store": "AYALA VERMOSA - BEBANG MEGA INC."
    }
  },
  {
    "kind": "order-create",
    "recordedAt": "2026-04-21T00:16:43.765Z",
    "payload": {
      "name": "BEI-ORD-2026-00404",
      "store": "BF HOMES - BEBANG BF HOMES INC."
    }
  },
  {
    "kind": "mr-create",
    "recordedAt": "2026-04-21T00:16:59.883Z",
    "payload": {
      "name": "MAT-MR-2026-00261",
      "store": "BF HOMES - BEBANG BF HOMES INC."
    }
  },
  {
    "kind": "wr-create",
    "recordedAt": "2026-04-21T00:17:17.757Z",
    "payload": {
      "name": "BEI-WHR-2026-00105",
      "store": "BF HOMES - BEBANG BF HOMES INC."
    }
  },
  {
    "kind": "si-create",
    "recordedAt": "2026-04-21T00:17:26.533Z",
    "payload": {
      "name": "ACC-SINV-2026-00094",
      "store": "BF HOMES - BEBANG BF HOMES INC."
    }
  },
  {
    "kind": "order-create",
    "recordedAt": "2026-04-21T00:17:44.251Z",
    "payload": {
      "name": "BEI-ORD-2026-00405",
      "store": "CTTM TOMAS MORATO - B CUBED VENTURES CORP."
    }
  },
  {
    "kind": "mr-create",
    "recordedAt": "2026-04-21T00:18:00.590Z",
    "payload": {
      "name": "MAT-MR-2026-00262",
      "store": "CTTM TOMAS MORATO - B CUBED VENTURES CORP."
    }
  }
]